gpx_concatenator/__init__.py
gpx_concatenator/gpx_colorizer.py
gpx_concatenator/gpx_concatenator.py
gpx_concatenator/gpx_file.py
gpx_concatenator/tests/__init__.py
gpx_concatenator/tests/gpx_colorizer_test.py
gpx_concatenator/tests/gpx_file_test.py
scripts/__init__.py
scripts/main.py
gpx_concatenator-1.0.8.dist-info/LICENSE
gpx_concatenator-1.0.8.dist-info/METADATA
gpx_concatenator-1.0.8.dist-info/WHEEL
gpx_concatenator-1.0.8.dist-info/entry_points.txt
gpx_concatenator-1.0.8.dist-info/top_level.txt
gpx_concatenator-1.0.8.dist-info/RECORD
