Metadata-Version: 2.1
Name: gpx-concatenator
Version: 1.0.8
Summary: Tool for concatenating GPX files
Author: iambrianna
Author-email: iambrianna@proton.me
License-File: LICENSE
